{
  "$schema": "https://turborepo.com/schema.json",
  "ui": "tui",
  "tasks": {
    "build": {
      "dependsOn": ["^build"],
      "inputs": ["$TURBO_DEFAULT$", ".env*"],
      "outputs": [".next/**", "!.next/cache/**"]
    },
    "lint": {
      "dependsOn": ["^lint"]
    },
    "check-types": {
      "dependsOn": ["^check-types"]
    },
    "test": {
      "dependsOn": [],
      "outputs": ["coverage/**"],
      "inputs": ["src/**/*.tsx", "src/**/*.ts", "test/**/*.ts"]
    },
    "dev": {
      "cache": false,
      "persistent": true
    }
  }
}
